[
    {
        "id": 37386,
        "list_id": "pre47_28_20",
        "データ取得日時": "2023-09-15 09:23:12",
        "都道府県": "沖縄県",
        "サロンのurl": "https://beauty.hotpepper.jp/slnH000202622/?cstt=560",
        "店舗名": "ビューティースタジオビア",
        "店舗名かな": "ビューティースタジオビア",
        "パンくず": "総合トップ  >   美容院・美容室・ヘアサロン検索トップ  >   九州・沖縄トップ  >   沖縄トップ  >   ビューティースタジオビア",
        "トップ画像数": 0,
        "キャッチコピー": "アットホームな雰囲気のちびっこ連れでもひとりでも緊張せずに、気軽に通えるアットホームなお店です。",
        "住所": "沖縄県沖縄市上地１－１２－１２ ",
        "アクセス・道案内": "「中の町」バス停から徒歩５分 ",
        "営業時間": "月～土・祝　10:00～18:00  TEL098-880-0852 ",
        "定休日": "毎週日曜日 ",
        "支払い方法": "現金のみ ",
        "カット価格": "¥3,300～ ",
        "席数": "セット面3席 ",
        "スタッフ数": "スタイリスト1人／アシスタント1人 ",
        "駐車場": "あり(店舗前) ",
        "こだわり条件": "４席以下の小型サロン／駐車場あり／ロング料金なし／最寄り駅から徒歩３分以内にある／一人のスタイリストが仕上げまで担当／ネイル／ヘアセット／朝１０時前でも受付OK／女性スタッフが多い／キッズスペースあり／お子さま同伴可／禁煙 ",
        "備考": "当日ご予約の際はお電話でお願いします！  できる限りご希望の時間帯をお取りできるよう努力します(*^^*)TEL  098-880-0852 ",
        "その他": "ポイント利用OK、即時予約OK、メンズにもオススメ",
        "電話番号": ""
    },
    {
        "id": 37387,
        "list_id": "pre47_29_1",
        "データ取得日時": "2023-09-15 09:23:13",
        "都道府県": "沖縄県",
        "サロンのurl": "https://beauty.hotpepper.jp/slnH000342720/?cstt=561",
        "店舗名": "美容室　結",
        "店舗名かな": "ビヨウシツ　ユイ",
        "パンくず": "総合トップ  >   美容院・美容室・ヘアサロン検索トップ  >   九州・沖縄トップ  >   沖縄トップ  >   美容室 結",
        "トップ画像数": 0,
        "キャッチコピー": "【恩納村】パーティーヘアセット￥3000★ブライダル経験豊富な実力派スタイリストが、幅広いStyleに対応♪",
        "住所": "沖縄県国頭郡恩納村字前兼久５１９ ",
        "アクセス・道案内": "サロンはムーンビーチホテル入口前にあります。「HabuBox恩納店」の隣です。 ",
        "営業時間": "9：00～19：00（早朝ヘアセットをご希望の方は、電話にてお問い合わせください） ",
        "定休日": "不定休 ",
        "支払い方法": "Visa／Mastercard／JCB／American Express／Diners Club／Discover／ApplePay iD QuickPay Alipay WeChatPay ",
        "カット価格": " ",
        "席数": "セット面2席 ",
        "スタッフ数": "スタイリスト1人 ",
        "駐車場": "あり（2台） ",
        "こだわり条件": "４席以下の小型サロン／駐車場あり／夜１９時以降も受付OK／一人のスタイリストが仕上げまで担当／ヘアセット／着付け／朝１０時前でも受付OK／店頭でのカード支払いOK／女性スタッフが多い／お子さま同伴可 ",
        "その他": "ポイント利用OK、即時予約OK",
        "電話番号": ""
    },
    {
        "id": 37388,
        "list_id": "pre47_29_2",
        "データ取得日時": "2023-09-15 09:23:14",
        "都道府県": "沖縄県",
        "サロンのurl": "https://beauty.hotpepper.jp/slnH000429691/?cstt=562",
        "店舗名": "頭皮ケア重視のヘアサロン Lita-lab【リタラボ】",
        "店舗名かな": "リタラボ",
        "パンくず": "総合トップ  >   美容院・美容室・ヘアサロン検索トップ  >   九州・沖縄トップ  >   沖縄トップ  >   リタラボ(Lita-lab)",
        "トップ画像数": 0,
        "キャッチコピー": "那覇市小禄/頭皮ケア重視サロン/毛髪診断士在籍/メンズ利用も歓迎/赤嶺駅徒歩2分",
        "住所": "沖縄県那覇市宇栄原１-２８-１０　赤嶺マンション２（１０１） ",
        "アクセス・道案内": "マンガ倉庫近く、グランドキャビンホテル（旧エトワス）裏。赤嶺駅からまんが倉庫左折、信号１つ超えた角に焼き鳥屋さんの「とりとん」を左へ。駐車場はHPに地図と動画ご覧ください。 ",
        "営業時間": "月・火・水・木・金・土(9：30～19：00) ",
        "定休日": "毎週日曜日 ",
        "支払い方法": "Visa／Mastercard／JCB／American Express／Diners Club／Discover ",
        "カット価格": "¥4,950 ",
        "席数": "セット面4席 ",
        "スタッフ数": "スタイリスト2人 ",
        "駐車場": "有り(3台) ",
        "こだわり条件": "４席以下の小型サロン／駐車場あり／ロング料金なし／最寄り駅から徒歩３分以内にある／ヘアセット／着付け／朝１０時前でも受付OK／店頭でのカード支払いOK／女性スタッフが多い／禁煙／ドリンクサービスあり／個室あり ",
        "その他": "ポイント利用OK、即時予約OK、メンズにもオススメ",
        "電話番号": ""
    },
    {
        "id": 37389,
        "list_id": "pre47_29_3",
        "データ取得日時": "2023-09-15 09:23:15",
        "都道府県": "沖縄県",
        "サロンのurl": "https://beauty.hotpepper.jp/slnH000330624/?cstt=563",
        "店舗名": "HAIR DESIGN  L.e.z.e.l.e.【ルゼル】",
        "店舗名かな": "ヘアーデザイン　ルゼル",
        "パンくず": "総合トップ  >   美容院・美容室・ヘアサロン検索トップ  >   九州・沖縄トップ  >   沖縄トップ  >   ヘアーデザイン ルゼル(HAIR DESIGN L.e.z.e.l.e.)",
        "トップ画像数": 0,
        "キャッチコピー": "【宜野湾市】オトナ女性にピッタリの隠れ家的サロン。実力派スタイリストが似合わせスタイルをご提案☆",
        "住所": "沖縄県宜野湾市喜友名1-31-10 ",
        "アクセス・道案内": "【那覇方面からお車でお越しの場合】国道58号線を北上し、大山を過ぎて、伊佐の交差点を宜野湾向けに右折。少し直進すると、ローソン宜野湾新城２丁目店がある信号を右折。ローソンの横の道に入るとすぐ右手側にサロンがあります。 ",
        "営業時間": "11:00～20:00 ",
        "定休日": "毎週火曜日/第三月曜日 ",
        "支払い方法": "Visa／Mastercard／JCB／American Express ",
        "カット価格": "¥4,950 ",
        "席数": "セット面3席 ",
        "スタッフ数": "スタイリスト1人 ",
        "駐車場": "店舗前に有 ",
        "こだわり条件": "４席以下の小型サロン／駐車場あり／ヘアセット／お子さま同伴可／禁煙／完全予約制 ",
        "その他": "ポイント利用OK、即時予約OK、メンズにもオススメ",
        "電話番号": ""
    },
    {
        "id": 37390,
        "list_id": "pre47_29_4",
        "データ取得日時": "2023-09-15 09:23:16",
        "都道府県": "沖縄県",
        "サロンのurl": "https://beauty.hotpepper.jp/slnH000522714/?cstt=564",
        "店舗名": "hair&spa -Abbey-　【アビー】",
        "店舗名かな": "ヘアーアンドスパ　アビー",
        "パンくず": "総合トップ  >   美容院・美容室・ヘアサロン検索トップ  >   九州・沖縄トップ  >   沖縄トップ  >   アビー(-Abbey-)",
        "トップ画像数": 0,
        "キャッチコピー": "”髪はほぼ、顔”　本気で髪のケアに向き合ってみませんか？頭皮環境を整えて5年後１０年後も美しい髪へ",
        "住所": "沖縄県宜野湾市真志喜６０６－４ ",
        "アクセス・道案内": "１，58号線那覇方面からお越しの際は真志喜南の信号左折→森川保育園を右折→すぐに左折50メートルほど先左手にございます。２，浦添西海岸道路からお越しの際は宇地泊IC左折→サンエーコンベンションシティとラウンドワン間を右折→ジャーダン左折→森川保育園左折→すぐに左折→50メートルほど先左手にございます。 ",
        "営業時間": "9:30～17:00【※施術中はお電話に出られないことがございます】 ",
        "定休日": "日、祝 ",
        "支払い方法": "Visa／Mastercard／JCB／American Express ",
        "カット価格": "¥7,700～ ",
        "席数": "セット面2席 ",
        "スタッフ数": "スタイリスト2人 ",
        "駐車場": "店前２台有 ",
        "こだわり条件": "４席以下の小型サロン／駐車場あり／一人のスタイリストが仕上げまで担当／朝１０時前でも受付OK／店頭でのカード支払いOK／女性スタッフが多い／お子さま同伴可／個室あり ",
        "その他": "ポイント利用OK、即時予約OK",
        "電話番号": ""
    },
    {
        "id": 37391,
        "list_id": "pre47_29_5",
        "データ取得日時": "2023-09-15 09:23:17",
        "都道府県": "沖縄県",
        "サロンのurl": "https://beauty.hotpepper.jp/slnH000475700/?cstt=565",
        "店舗名": "tayutaw【タユタウ】",
        "店舗名かな": "タユタウ",
        "パンくず": "総合トップ  >   美容院・美容室・ヘアサロン検索トップ  >   九州・沖縄トップ  >   沖縄トップ  >   タユタウ(tayutaw)",
        "トップ画像数": 0,
        "キャッチコピー": "[マンツーマンサロン]ホットペッパービューティー限定クーポンあり◎当日予約可能",
        "住所": "沖縄県沖縄市古謝１‐3‐52　SOJ BLDG2-A ",
        "アクセス・道案内": "【美里大通り（県道75号）から】美里郵便局・ミスタードーナツさんの通りに入り（224号）直進。右手のユニオン宮里さんから約1Kmを右折。【アワセベイストリート（県道85号）から】海邦公園の交差点を古謝向けに直進。左手のローソン古謝さんから約1Kmを左折。坂の途中のピンクの建物。店舗下2番が駐車場です。 ",
        "営業時間": "月～土日/祝日　9：00～19：00 ",
        "定休日": "不定休 ",
        "支払い方法": "Visa／Mastercard／JCB／American Express／Diners Club／Discover ",
        "カット価格": "¥3,500 ",
        "席数": "セット面1席 ",
        "スタッフ数": "スタイリスト1人 ",
        "駐車場": "1台（2番） ",
        "こだわり条件": "４席以下の小型サロン／駐車場あり／一人のスタイリストが仕上げまで担当／ヘアセット／朝１０時前でも受付OK／店頭でのカード支払いOK／女性スタッフが多い／ドリンクサービスあり／完全予約制 ",
        "備考": "スタイリスト１人のため、薬剤を使う施術中のお電話に出られない場合がございます。後ほどこちらからお電話をかけ直させていただきますので、ご協力よろしくお願いします。 ",
        "その他": "ポイント利用OK、即時予約OK",
        "電話番号": ""
    },
    {
        "id": 37392,
        "list_id": "pre47_29_6",
        "データ取得日時": "2023-09-15 09:23:18",
        "都道府県": "沖縄県",
        "サロンのurl": "https://beauty.hotpepper.jp/slnH000485665/?cstt=566",
        "店舗名": "hair salon CoCopeace【ココピース】",
        "店舗名かな": "ヘアーサロンココピース",
        "パンくず": "総合トップ  >   美容院・美容室・ヘアサロン検索トップ  >   九州・沖縄トップ  >   沖縄トップ  >   ココピース(hair salon CoCopeace)",
        "トップ画像数": 0,
        "キャッチコピー": "【感染拡大防止対策行っています】居心地のいいプライベートサロン★",
        "住所": "沖縄県南城市大里稲嶺78-1　1F ",
        "アクセス・道案内": "稲嶺十字路を八重瀬町向けに180ｍ、県道77号線沿いになります。店舗1Fになります。　　TEL090-9169ー6462 ",
        "営業時間": "　9：00-18：00(カット最終受付17：00) ",
        "定休日": "月曜日 ",
        "支払い方法": " ",
        "カット価格": "¥3,500 ",
        "席数": "セット面2席 ",
        "スタッフ数": "スタイリスト1人 ",
        "駐車場": "有 ",
        "こだわり条件": "４席以下の小型サロン／駐車場あり／一人のスタイリストが仕上げまで担当／ヘアセット／着付け／朝１０時前でも受付OK／キッズスペースあり／お子さま同伴可／禁煙／DVDが観られる ",
        "備考": "ネット予約できない時でも予約可能な場合もございますのでお電話下さい。お子様同伴OK♪ ",
        "その他": "ポイント利用OK、即時予約OK",
        "電話番号": ""
    },
    {
        "id": 37393,
        "list_id": "pre47_29_7",
        "データ取得日時": "2023-09-15 09:23:19",
        "都道府県": "沖縄県",
        "サロンのurl": "https://beauty.hotpepper.jp/slnH000232004/?cstt=567",
        "店舗名": "siesta 【シエスタ】",
        "店舗名かな": "シエスタ",
        "パンくず": "総合トップ  >   美容院・美容室・ヘアサロン検索トップ  >   九州・沖縄トップ  >   沖縄トップ  >   シエスタ(siesta)",
        "トップ画像数": 0,
        "キャッチコピー": "【那覇】光の差し込む店内にあなただけの特別席が。誰にも教えたくない…あなただけのとっておきのサロン",
        "住所": "沖縄県那覇市壺屋１-30-16 ",
        "アクセス・道案内": "【お車の方】やむちん通りを東に向かい、ひめゆり通り手前の小道を右に曲がると左手に駐車場が見えます。気軽にお電話にてお問い合わせください。【徒歩の方】ひめゆり通りのマクドナルドの向かいの小道を入っていくとすぐにあります。気軽にお電話にてお問い合わせください。 ",
        "営業時間": "受付時間10：00～パーマ・カラー最終受付ｐｍ18：30 カット最終受付ｐｍ19：30まで ※前もってご連絡いただければ上記時間外でもOKです。気軽にお問い合わせください。 ",
        "定休日": "不定休 ",
        "支払い方法": "Visa／Mastercard／American Express ",
        "カット価格": "¥4,000 ",
        "席数": "セット面2席 ",
        "スタッフ数": "スタイリスト1人 ",
        "駐車場": "2台 ",
        "こだわり条件": "４席以下の小型サロン／駐車場あり／一人のスタイリストが仕上げまで担当／お子さま同伴可／禁煙／ドリンクサービスあり ",
        "その他": "ポイント利用OK、即時予約OK、メンズにもオススメ",
        "電話番号": ""
    },
    {
        "id": 37394,
        "list_id": "pre47_29_8",
        "データ取得日時": "2023-09-15 09:23:20",
        "都道府県": "沖縄県",
        "サロンのurl": "https://beauty.hotpepper.jp/slnH000596192/?cstt=568",
        "店舗名": "ONE SCISSORS【ワンシザース】",
        "店舗名かな": "ワン　シザース",
        "パンくず": "総合トップ  >   美容院・美容室・ヘアサロン検索トップ  >   九州・沖縄トップ  >   沖縄トップ  >   ワンシザース(ONE SCISSORS)",
        "トップ画像数": 0,
        "キャッチコピー": "【シンプルイズベストな施術とサロン】技術の高さとこだわり抜いた商材で理想のスタイリングを叶えます。",
        "住所": "沖縄県那覇市首里鳥堀町１－４６－２　２F ",
        "アクセス・道案内": "鳥堀十字路の角　2階 ",
        "営業時間": "月～金：11時00分～20時00分　土：9時00分～19時00分 ",
        "定休日": "日曜 ",
        "支払い方法": "Visa／Mastercard／JCB／American Express／UnionPay（銀聯）／QR決済 ",
        "カット価格": "¥2,750～ ",
        "席数": "セット面4席 ",
        "スタッフ数": "スタイリスト1人／アシスタント1人 ",
        "駐車場": "4台 ",
        "こだわり条件": "４席以下の小型サロン／駐車場あり／最寄り駅から徒歩３分以内にある／店頭でのカード支払いOK／男性スタッフが多い／お子さま同伴可／分煙／ドリンクサービスあり ",
        "備考": "駐車場案内『コーポ大城　首里』で検索するとナビがでます。そこの向かいの駐車場の1、3、11、12番に駐車できます。ブルーグレーのブロックが目印です。TEL 098-800-2246 ",
        "その他": "ポイント利用OK、即時予約OK、メンズにもオススメ",
        "電話番号": ""
    },
    {
        "id": 37394,
        "list_id": "pre47_29_9",
        "データ取得日時": "2023-09-15 09:23:21",
        "都道府県": "沖縄県",
        "サロンのurl": "https://beauty.hotpepper.jp/slnH000238096/?cstt=569",
        "店舗名": "ICHICONCHI 【イチコンチ】",
        "店舗名かな": "イチコンチ",
        "パンくず": "総合トップ  >   美容院・美容室・ヘアサロン検索トップ  >   九州・沖縄トップ  >   沖縄トップ  >   イチコンチ(ICHICONCHI)",
        "トップ画像数": 0,
        "キャッチコピー": "1人のスタッフが全て担当します",
        "住所": "沖縄県豊見城市宜保361ピースビル103 ",
        "アクセス・道案内": "沖縄県豊見城市字宜保4丁目2番地11 ピースビル103※豊見城中央病院、平和台北口バス停近く ",
        "営業時間": "10:00～20:00 （最終受付 19:00） ",
        "定休日": "6月より火曜日から水曜日に変更なりました ",
        "支払い方法": "Visa／Mastercard／PayPay、Edy、iD、nanaco、WAON、Suica、 ",
        "カット価格": "¥3,670 ",
        "席数": "セット面3席 ",
        "スタッフ数": "スタイリスト1人 ",
        "駐車場": "2台あり ",
        "こだわり条件": "４席以下の小型サロン／駐車場あり／一人のスタイリストが仕上げまで担当／ヘアセット／着付け／店頭でのカード支払いOK／お子さま同伴可／禁煙／ドリンクサービスあり／DVDが観られる／完全予約制 ",
        "その他": "ポイント利用OK、即時予約OK、メンズにもオススメ",
        "電話番号": ""
    }
]