[
    {
        "hall_name": "Accueillir　風彩の森迎賓館（アクイール　かぜのもりげいひんかん）",
        "hall_url": "https://zexy.net//wedding/c_7770062338/?inrlead=arealist_hall_link&clRank=1",
        "detail": true
    },
    {
        "hall_name": "KASANE YONAGO",
        "hall_url": "https://zexy.net//wedding/c_7770060850/?inrlead=arealist_hall_link&clRank=2",
        "detail": true
    },
    {
        "hall_name": "三瀧荘",
        "hall_url": "https://zexy.net//wedding/c_7770014134/",
        "detail": true
    },
    {
        "hall_name": "広島サンプラザ",
        "hall_url": "https://zexy.net//wedding/c_7770031375/",
        "detail": false
    },
    {
        "hall_name": "Ｗ ザ ブライズ スイート",
        "hall_url": "https://zexy.net//wedding/c_7770055553/",
        "detail": true
    },
    {
        "hall_name": "Recent Culture Hotel（リーセントカルチャーホテル）",
        "hall_url": "https://zexy.net//wedding/c_7770023529/",
        "detail": true
    },
    {
        "hall_name": "ポピースプリングス　リゾート＆スパ",
        "hall_url": "https://zexy.net//wedding/c_7770076494/",
        "detail": false
    },
    {
        "hall_name": "広島グランドインテリジェントホテル",
        "hall_url": "https://zexy.net//wedding/c_7770030252/",
        "detail": false
    },
    {
        "hall_name": "ブライダルハウス「写樂庭」（あけぼのスタジオ）",
        "hall_url": "https://zexy.net//wedding/c_7770037167/",
        "detail": false
    },
    {
        "hall_name": "ティアラ・ザ クラシッククラブ",
        "hall_url": "https://zexy.net//wedding/c_7770044286/",
        "detail": true
    },
    {
        "hall_name": "ララシャンス HIROSHIMA迎賓館",
        "hall_url": "https://zexy.net//wedding/c_7770072710/",
        "detail": true
    },
    {
        "hall_name": "エルセルモ広島",
        "hall_url": "https://zexy.net//wedding/c_7770027541/",
        "detail": true
    }
]